MANIFEST.in
README.md
requirements.txt
setup.cfg
setup.py
tasix/__init__.py
tasix.egg-info/PKG-INFO
tasix.egg-info/SOURCES.txt
tasix.egg-info/dependency_links.txt
tasix.egg-info/requires.txt
tasix.egg-info/top_level.txt