Metadata-Version: 1.1
Name: tasix
Version: 0.0.1
Summary: Tas-IX package
Home-page: https://github.com/muminoff/tasix
Author: Sardor Muminov
Author-email: smuminov@gmail.com
License: BSD
Download-URL: https://github.com/muminoff/tasix/tarball/0.0.1
Platform: UNKNOWN
Classifier: Development Status :: 3 - Alpha
Classifier: Intended Audience :: Developers
Classifier: Programming Language :: Python :: 3
